Workbook

Sheet Datos de Ventas
A1: 📊 Análisis de Ventas Mensuales 2024 – Proyecto Excel con IA
A2: Pregunta clave: ¿En qué mes se proyectan mayores ventas y cuál es la tendencia del año?
A4: Mes | B4: Ventas Reales ($) | C4: Meta ($) | D4: Costo ($) | E4: Utilidad ($) | F4: % Cumplimiento | G4: % Margen
A5: Enero | B5: 42500 | C5: 45000 | D5: 28900 | E5: =B5-D5 -> 13600 | F5: =B5/C5 -> 0.94444444 | G5: =E5/B5 -> 0.32
A6: Febrero | B6: 38700 | C6: 45000 | D6: 26400 | E6: =B6-D6 -> 12300 | F6: =B6/C6 -> 0.86 | G6: =E6/B6 -> 0.31782946
A7: Marzo | B7: 51200 | C7: 50000 | D7: 34800 | E7: =B7-D7 -> 16400 | F7: =B7/C7 -> 1.024 | G7: =E7/B7 -> 0.3203125
A8: Abril | B8: 47800 | C8: 50000 | D8: 32500 | E8: =B8-D8 -> 15300 | F8: =B8/C8 -> 0.956 | G8: =E8/B8 -> 0.32008368
A9: Mayo | B9: 55300 | C9: 55000 | D9: 37600 | E9: =B9-D9 -> 17700 | F9: =B9/C9 -> 1.0054545 | G9: =E9/B9 -> 0.32007233
A10: Junio | B10: 61400 | C10: 60000 | D10: 41800 | E10: =B10-D10 -> 19600 | F10: =B10/C10 -> 1.0233333 | G10: =E10/B10 -> 0.31921824
A11: Julio | B11: 58900 | C11: 60000 | D11: 40100 | E11: =B11-D11 -> 18800 | F11: =B11/C11 -> 0.98166667 | G11: =E11/B11 -> 0.31918506
A12: Agosto | B12: 63200 | C12: 65000 | D12: 43000 | E12: =B12-D12 -> 20200 | F12: =B12/C12 -> 0.97230769 | G12: =E12/B12 -> 0.31962025
A13: Septiembre | B13: 67800 | C13: 70000 | D13: 46200 | E13: =B13-D13 -> 21600 | F13: =B13/C13 -> 0.96857143 | G13: =E13/B13 -> 0.31858407
A14: Octubre | B14: 72100 | C14: 75000 | D14: 49100 | E14: =B14-D14 -> 23000 | F14: =B14/C14 -> 0.96133333 | G14: =E14/B14 -> 0.31900139
A15: Noviembre | B15: 81500 | C15: 80000 | D15: 55500 | E15: =B15-D15 -> 26000 | F15: =B15/C15 -> 1.01875 | G15: =E15/B15 -> 0.3190184
A16: Diciembre | B16: 95300 | C16: 90000 | D16: 64900 | E16: =B16-D16 -> 30400 | F16: =B16/C16 -> 1.0588889 | G16: =E16/B16 -> 0.31899265
A17: TOTAL ANUAL | B17: =SUM(B5:B16) -> 735700 | C17: =SUM(C5:C16) -> 745000 | D17: =SUM(D5:D16) -> 500800 | E17: =SUM(E5:E16) -> 234900 | F17: =SUM(F5:F16) -> 11.77475 | G17: =SUM(G5:G16) -> 3.831918
A19: 📌 Indicadores Clave (KPIs)
A20: Mes con Mayor Venta | B20: =INDEX(A5:A16,MATCH(MAX(B5:B16),B5:B16,0)) -> Diciembre
A21: Mes con Menor Venta | B21: =INDEX(A5:A16,MATCH(MIN(B5:B16),B5:B16,0)) -> Febrero
A22: Promedio Mensual ($) | B22: =AVERAGE(B5:B16) -> 61308.333
A23: Mejor % Cumplimiento | B23: =MAX(F5:F16) -> 1.0588889
A24: Mejor % Margen | B24: =MAX(G5:G16) -> 0.3203125

Sheet Pronóstico IA
A1: 🤖 Pronóstico con IA – Función FORECAST.ETS (Excel)
A2: Esta hoja usa FORECAST.ETS — la función de IA de Excel basada en suavización exponencial para detectar tendencia y estacionalidad.
A4: Período | B4: Mes | C4: Ventas Reales ($) | D4: Pronóstico IA ($) | E4: Límite Inferior ($) | F4: Límite Superior ($)
A5: 1 | B5: Enero | C5: 42500
A6: 2 | B6: Febrero | C6: 38700
A7: 3 | B7: Marzo | C7: 51200
A8: 4 | B8: Abril | C8: 47800
A9: 5 | B9: Mayo | C9: 55300
A10: 6 | B10: Junio | C10: 61400
A11: 7 | B11: Julio | C11: 58900
A12: 8 | B12: Agosto | C12: 63200
A13: 9 | B13: Septiembre | C13: 67800
A14: 10 | B14: Octubre | C14: 72100
A15: 11 | B15: Noviembre | C15: 81500
A16: 12 | B16: Diciembre | C16: 95300
A17: 13 | B17: Enero 2025 | D17: =forecast.ets(A17,'Datos de Ventas'!B5:B16,'Datos de Ventas'!A5:A16,1,1) -> #NAME? | E17: =forecast.ets.confint(A17,'Datos de Ventas'!B5:B16,'Datos de Ventas'!A5:A16,0.95,1,1) -> #NAME? | F17: =D17+E17 -> #NAME?
A18: 14 | B18: Febrero 2025 | D18: =forecast.ets(A18,'Datos de Ventas'!B5:B16,'Datos de Ventas'!A5:A16,1,1) -> #NAME? | E18: =forecast.ets.confint(A18,'Datos de Ventas'!B5:B16,'Datos de Ventas'!A5:A16,0.95,1,1) -> #NAME? | F18: =D18+E18 -> #NAME?
A19: 15 | B19: Marzo 2025 | D19: =forecast.ets(A19,'Datos de Ventas'!B5:B16,'Datos de Ventas'!A5:A16,1,1) -> #NAME? | E19: =forecast.ets.confint(A19,'Datos de Ventas'!B5:B16,'Datos de Ventas'!A5:A16,0.95,1,1) -> #NAME? | F19: =D19+E19 -> #NAME?
A20: 16 | B20: Abril 2025 | D20: =forecast.ets(A20,'Datos de Ventas'!B5:B16,'Datos de Ventas'!A5:A16,1,1) -> #NAME? | E20: =forecast.ets.confint(A20,'Datos de Ventas'!B5:B16,'Datos de Ventas'!A5:A16,0.95,1,1) -> #NAME? | F20: =D20+E20 -> #NAME?

Sheet Gráficos y Análisis
A1: 📈 Visualizaciones del Análisis de Ventas
A2: Los gráficos fueron generados con las funciones de Ideas y gráficos automáticos de Excel

Sheet Resumen Trimestral
A1: 📋 Resumen Trimestral – Tabla Dinámica
A2: Análisis por trimestre para identificar estacionalidad
A4: Trimestre | B4: Meses | C4: Ventas Totales ($) | D4: Utilidad Total ($) | E4: % Margen Prom.
A5: Q1 – Ene/Feb/Mar | B5: Enero, Febrero, Marzo | C5: =SUM('Datos de Ventas'!B5:B7) -> 132400 | D5: =SUM('Datos de Ventas'!E5:E7) -> 42300 | E5: =AVERAGE('Datos de Ventas'!G5:G7) -> 0.31938065
A6: Q2 – Abr/May/Jun | B6: Abril, Mayo, Junio | C6: =SUM('Datos de Ventas'!B8:B10) -> 164500 | D6: =SUM('Datos de Ventas'!E8:E10) -> 52600 | E6: =AVERAGE('Datos de Ventas'!G8:G10) -> 0.31979142
A7: Q3 – Jul/Ago/Sep | B7: Julio, Agosto, Septiembre | C7: =SUM('Datos de Ventas'!B11:B13) -> 189900 | D7: =SUM('Datos de Ventas'!E11:E13) -> 60600 | E7: =AVERAGE('Datos de Ventas'!G11:G13) -> 0.31912979
A8: Q4 – Oct/Nov/Dic | B8: Octubre, Noviembre, Diciembre | C8: =SUM('Datos de Ventas'!B14:B16) -> 248900 | D8: =SUM('Datos de Ventas'!E14:E16) -> 79400 | E8: =AVERAGE('Datos de Ventas'!G14:G16) -> 0.31900415
A9: TOTAL AÑO | B9: Todos los meses | C9: =SUM(C5:C8) -> 735700 | D9: =SUM(D5:D8) -> 234900 | E9: =AVERAGE(E5:E8) -> 0.3193265

Sheet Documentación
A1: 📝 Documentación del Proyecto – Domina Excel con IA
A3: 🎯 Tema Elegido
B4: Análisis de Ventas Mensuales 2024
B5: Se analizan las ventas reales de una empresa durante 12 meses, comparando con metas establecidas y proyectando el comportamiento para los primeros meses de 2025.
A7: ❓ Pregunta Clave
B8: ¿En qué mes se proyectan mayores ventas y cuál es la tendencia del año?
B9: Respuesta: Según el pronóstico de IA (FORECAST.ETS), los meses de enero-abril 2025 muestran una tendencia creciente con base en la estacionalidad detectada.
A11: 📂 Fuente de Datos
B12: Datos simulados que representan un modelo de ventas realista.
B13: La estructura sigue el patrón de una empresa mediana con estacionalidad en Q4.
B14: Formato: Tabla Excel con 12 filas (una por mes) y 7 columnas de indicadores.
A16: 🤖 Herramientas de IA Usadas
B17: 1. FORECAST.ETS: Función nativa de Excel basada en algoritmos de suavización exponencial (AAA-ETS). Detecta tendencia y estacionalidad automáticamente.
B18: 2. FORECAST.ETS.CONFINT: Calcula el intervalo de confianza al 95% del pronóstico.
B19: 3. IDEAS DE EXCEL: Función de análisis automático (pestaña Inicio → Ideas) que sugiere gráficos y patrones relevantes.
B20: 4. INDEX + MATCH: Para identificar automáticamente el mes con mayor y menor venta.
B21: 5. Gráficos automáticos sugeridos por Excel al seleccionar los datos.
A23: 📊 Visualizaciones Generadas
B24: 1. Gráfico de barras agrupadas: Ventas Reales vs Meta mensual (Hoja 'Gráficos y Análisis').
B25: 2. Gráfico de línea: Evolución de la Utilidad mensual.
B26: 3. Gráfico de pastel: Distribución de ventas por trimestre (Hoja 'Resumen Trimestral').
B27: 4. Tabla dinámica manual con resumen por trimestre.
A29: 💡 Conclusiones del Análisis
B30: 1. El Q4 (Oct-Dic) concentra las mayores ventas, representando aproximadamente el 35% del total anual.
B31: 2. Diciembre es el mes de mayor venta ($95,300) superando la meta en un 5.9%.
B32: 3. Febrero registra la menor venta ($38,700), por debajo de la meta en 14%.
B33: 4. El margen de utilidad promedio anual es del 31%, manteniéndose estable.
B34: 5. El pronóstico de IA indica que la tendencia al alza continuará en 2025.
B35: 6. El modelo de IA detectó estacionalidad positiva en los últimos meses del año.
A37: 🛠️ Instrucciones de Uso
B38: 1. Abrir el archivo en Microsoft Excel 365 o Excel 2019+.
B39: 2. Si aparece aviso de seguridad, habilitar edición y contenido.
B40: 3. Los pronósticos en la hoja 'Pronóstico IA' se calculan automáticamente con FORECAST.ETS.
B41: 4. Para ver 'Ideas de Excel': seleccionar los datos en 'Datos de Ventas' → pestaña Inicio → Ideas.
B42: 5. Los KPIs en la hoja principal se actualizan automáticamente al cambiar los datos.
